{"commitInfo":{"timestamp":1773197468890,"operation":"STREAMING UPDATE","operationParameters":{"outputMode":"Append","queryId":"d2792382-e8e8-4985-9ea4-6daa8d2cd07b","epochId":"58"},"readVersion":57,"isolationLevel":"Serializable","isBlindAppend":true,"operationMetrics":{"numRemovedFiles":"0","numOutputRows":"0","numOutputBytes":"490","numAddedFiles":"0"},"engineInfo":"Apache-Spark/3.5.8 Delta-Lake/3.2.0","txnId":"e2c87793-9bdb-4a1d-a004-e1ae65aac420"}}
{"txn":{"appId":"d2792382-e8e8-4985-9ea4-6daa8d2cd07b","version":58,"lastUpdated":1773197468889}}
