{"commitInfo":{"timestamp":1773203606623,"operation":"STREAMING UPDATE","operationParameters":{"outputMode":"Append","queryId":"eb11b06c-6931-4366-9aaa-cc0f51ce408f","epochId":"173"},"readVersion":172,"isolationLevel":"Serializable","isBlindAppend":true,"operationMetrics":{"numRemovedFiles":"0","numOutputRows":"0","numOutputBytes":"490","numAddedFiles":"0"},"engineInfo":"Apache-Spark/3.5.8 Delta-Lake/3.2.0","txnId":"f3667708-281f-46aa-a2b5-eb7221fb11aa"}}
{"txn":{"appId":"eb11b06c-6931-4366-9aaa-cc0f51ce408f","version":173,"lastUpdated":1773203606622}}
