{"commitInfo":{"timestamp":1773204109108,"operation":"STREAMING UPDATE","operationParameters":{"outputMode":"Append","queryId":"eb11b06c-6931-4366-9aaa-cc0f51ce408f","epochId":"239"},"readVersion":238,"isolationLevel":"Serializable","isBlindAppend":true,"operationMetrics":{"numRemovedFiles":"0","numOutputRows":"0","numOutputBytes":"490","numAddedFiles":"0"},"engineInfo":"Apache-Spark/3.5.8 Delta-Lake/3.2.0","txnId":"54e2f17a-03c3-43df-955c-420eee0b739c"}}
{"txn":{"appId":"eb11b06c-6931-4366-9aaa-cc0f51ce408f","version":239,"lastUpdated":1773204109108}}
